<!-- system icons: ./system-controllers-outline/${system.theme}.svg ; logos: ./system-logos/system-logo-white/${system.theme}.svg (color: ./system-logos/system-logo-color/${system.theme}.svg) ; metadata: ./system-metadata/${system.theme}.xml -->
<theme>
    <include>./_inc/fonts.xml</include>
    <include>./_inc/colors.xml</include>

    <variant name="heroNeonGrid">
        <include>./_inc/system_hero_neon.xml</include>
        <include>./_inc/gamelist_grid.xml</include>
    </variant>
    <variant name="heroNeonList">
        <include>./_inc/system_hero_neon.xml</include>
        <include>./_inc/gamelist_list.xml</include>
    </variant>
    <variant name="heroArtGrid">
        <include>./_inc/system_hero_art.xml</include>
        <include>./_inc/gamelist_grid.xml</include>
    </variant>
    <variant name="heroArtList">
        <include>./_inc/system_hero_art.xml</include>
        <include>./_inc/gamelist_list.xml</include>
    </variant>
    <variant name="noHeroGrid">
        <include>./_inc/system_nohero.xml</include>
        <include>./_inc/gamelist_grid.xml</include>
    </variant>
    <variant name="noHeroList">
        <include>./_inc/system_nohero.xml</include>
        <include>./_inc/gamelist_list.xml</include>
    </variant>
</theme>
